ustb_openai/__init__.py
ustb_openai/_client.py
ustb_openai/_exceptions.py
ustb_openai/_models.py
ustb_openai/_utils/__init__.py
ustb_openai/_utils/form_request_builder.py
ustb_openai/_utils/openai_stream_adaptor.py
ustb_openai/api_models/__init__.py
ustb_openai/api_models/chat_history_info.py
ustb_openai/api_models/compose_chat.py
ustb_openai/api_models/compose_detail.py
ustb_openai/api_models/compose_list.py
ustb_openai/api_models/page_settings.py
ustb_openai/api_models/session_delete.py
ustb_openai/api_models/session_list.py
ustb_openai/api_models/session_new.py
ustb_openai/api_models/user_info.py
ustb_openai/api_models/web_info.py
ustb_openai/resources/__init__.py
ustb_openai/resources/chat/__init__.py
ustb_openai/resources/chat/chat.py
ustb_openai/resources/chat/completions/__init__.py
ustb_openai/resources/chat/completions/completions.py
ustb_openai/resources/info/__init__.py
ustb_openai/resources/info/info.py
ustb_openai/types/__init__.py
ustb_openai/types/chat/__init__.py
ustb_openai/types/chat/chat_completion.py
ustb_openai-1.1.0.dist-info/LICENSE
ustb_openai-1.1.0.dist-info/METADATA
ustb_openai-1.1.0.dist-info/WHEEL
ustb_openai-1.1.0.dist-info/RECORD
