Metadata-Version: 2.3
Name: USTB-OpenAI
Version: 1.1.0
Summary: OpenAI style API for accessing the USTB hosted LLM
License: MIT
Author: Harry Huang
Author-email: harryhuang2652@qq.com
Requires-Python: >=3.8,<4
Classifier: Programming Language :: Python :: 3
Classifier: License :: OSI Approved :: MIT License
Classifier: Operating System :: OS Independent
Provides-Extra: ustb-sso
Requires-Dist: httpx (>=0.28,<1.0)
Requires-Dist: httpx-sse (>=0.4,<1.0)
Requires-Dist: pydantic (>=2.10,<3.0)
Requires-Dist: ustb-sso (>=1.1) ; extra == "ustb-sso"
